ipstack/__init__.py
ipstack/geolookup.py
ipstack-0.1.4.dist-info/LICENSE
ipstack-0.1.4.dist-info/METADATA
ipstack-0.1.4.dist-info/WHEEL
ipstack-0.1.4.dist-info/top_level.txt
ipstack-0.1.4.dist-info/RECORD
