Metadata-Version: 2.1
Name: ipstack
Version: 0.1.4
Summary: A Python library for interfacing with IPStack Geo API
Home-page: https://github.com/nathan-fiscaletti/ipstackgeo-py
Author: Nathan Fiscaletti
Author-email: nathan.fiscaletti@gmail.com
License: UNKNOWN
Platform: UNKNOWN
Classifier: Programming Language :: Python :: 2.7
Classifier: Programming Language :: Python :: 3.7
Classifier: License :: OSI Approved :: MIT License
Classifier: Operating System :: OS Independent
